dfaRunner/__init__.py
dfaRunner/main.py
dfa_runner-0.0.0.dist-info/licenses/LICENSE
dfa_runner-0.0.0.dist-info/METADATA
dfa_runner-0.0.0.dist-info/WHEEL
dfa_runner-0.0.0.dist-info/entry_points.txt
dfa_runner-0.0.0.dist-info/top_level.txt
dfa_runner-0.0.0.dist-info/RECORD
