Metadata-Version: 2.4
Name: dfa-runner
Version: 0.0.0
Summary: Run words through A DFA specified in a given toml file
Author-email: Christian Haastrup <chaastrup865@gmail.com>
License-File: LICENSE
Requires-Dist: toml
Dynamic: license-file
